interest_measures/__init__.py
interest_measures/_interest_measures.py
interest_measures-0.0.2.dist-info/METADATA
interest_measures-0.0.2.dist-info/WHEEL
interest_measures-0.0.2.dist-info/RECORD
